simple_tcp/__init__.py
simple_tcp/__main__.py
simple_tcp-0.6.dist-info/LICENSE
simple_tcp-0.6.dist-info/METADATA
simple_tcp-0.6.dist-info/WHEEL
simple_tcp-0.6.dist-info/top_level.txt
simple_tcp-0.6.dist-info/RECORD
