Metadata-Version: 2.1
Name: simple-tcp
Version: 0.6
Summary: A simple TCP client and server for easy testing
Home-page: https://gitlab.com/kristiant/simple_tcp
Author: Kristian Tanuwijaya
Author-email: tanuwijaya.kristian@gmail.com
License: UNKNOWN
Platform: UNKNOWN
Classifier: Programming Language :: Python :: 3
Classifier: License :: OSI Approved :: MIT License
Classifier: Operating System :: OS Independent
